toga_django/__init__.py
toga_django/app.py
toga_django/bootstrap.py
toga_django/container.py
toga_django/dialogs.py
toga_django/window.py
toga_django/django/__init__.py
toga_django/django/templates/toga/app.html
toga_django/django/templates/toga/base.html
toga_django/django/templates/toga/window.html
toga_django/impl/__init__.py
toga_django/impl/app.py
toga_django/impl/box.py
toga_django/impl/button.py
toga_django/impl/label.py
toga_django/impl/list.py
toga_django/impl/textinput.py
toga_django/impl/webview.py
toga_django/impl/window.py
toga_django/widgets/__init__.py
toga_django/widgets/base.py
toga_django/widgets/box.py
toga_django/widgets/button.py
toga_django/widgets/label.py
toga_django/widgets/list.py
toga_django/widgets/textinput.py
toga_django/widgets/webview.py
toga_django-0.2.15.dist-info/DESCRIPTION.rst
toga_django-0.2.15.dist-info/METADATA
toga_django-0.2.15.dist-info/RECORD
toga_django-0.2.15.dist-info/WHEEL
toga_django-0.2.15.dist-info/metadata.json
toga_django-0.2.15.dist-info/pbr.json
toga_django-0.2.15.dist-info/top_level.txt
