Metadata-Version: 1.1
Name: toga-django
Version: 0.2.15
Summary: A Django backend for the Toga widget toolkit.
Home-page: http://pybee.org/toga
Author: Russell Keith-Magee
Author-email: russell@keith-magee.com
License: New BSD
Platform: UNKNOWN
Classifier: Development Status :: 3 - Alpha
Classifier: Intended Audience :: Developers
Classifier: License :: OSI Approved :: BSD License
Classifier: Environment :: MacOS X :: Cocoa
Classifier: Programming Language :: Python :: 3
Classifier: Programming Language :: Python :: 3.4
Classifier: Programming Language :: Python :: 3.5
Classifier: Programming Language :: Python :: 3 :: Only
Classifier: Topic :: Software Development
Classifier: Topic :: Software Development :: User Interfaces
Classifier: Topic :: Software Development :: Widget Sets
